main.py
build/lib/main.py
netmind_mcp_stampit-1.1.1.dist-info/licenses/LICENSE
netmind_mcp_stampit-1.1.1.dist-info/METADATA
netmind_mcp_stampit-1.1.1.dist-info/WHEEL
netmind_mcp_stampit-1.1.1.dist-info/entry_points.txt
netmind_mcp_stampit-1.1.1.dist-info/top_level.txt
netmind_mcp_stampit-1.1.1.dist-info/RECORD
